setup.py
agent_reporter.egg-info/PKG-INFO
agent_reporter.egg-info/SOURCES.txt
agent_reporter.egg-info/dependency_links.txt
agent_reporter.egg-info/requires.txt
agent_reporter.egg-info/top_level.txt
reporter/__init__.py
reporter/event_reporter.py
scripts/agent-reporter