Metadata-Version: 1.0
Name: agent-reporter
Version: 0.0.7
Summary: Agent Reporter
Home-page: UNKNOWN
Author: UNKNOWN
Author-email: UNKNOWN
License: __license__
Platform: UNKNOWN
